{
    "title": "Optimized Externe Datenschutzbeauftragte Features",
    "intro": "This list represents the optimized features of Externe Datenschutzbeauftragte, gathered from analyzing 23 sites and 133 features.",
    "features": {
        "Datenschutz-Expertise": {
            "title": "Expertise",
            "features": [
                "Juristen mit notwendiger Fachkunde und langj\u00e4hriger Berufserfahrung im Datenschutzrecht (23)"
            ]
        },
        "IT-Kenntnisse": {
            "title": "IT-Kenntnisse",
            "features": [
                "Technische Umsetzung der rechtlichen Vorgaben (23)"
            ]
        },
        "Erfahrung und Expertise": {
            "title": "Erfahrung und Expertise",
            "features": [
                "Vielf\u00e4ltige Erfahrung in Datenschutz-L\u00f6sungen f\u00fcr Unternehmen jeder Gr\u00f6\u00dfe und verschiedenster Branchen (23)",
                "Langj\u00e4hrige Berufserfahrung im Datenschutzrecht und entsprechend spezialisiert (23)",
                "Branchenspezifische Datenschutzexpertise (23)",
                "Branchen\u00fcbergreifende Erfahrung (23)",
                "Umfassende Kenntnisse der Branchenspezifika und technologischen Systeme (23)"
            ]
        },
        "Beratung und Schulung": {
            "title": "Beratung und Schulung",
            "features": [
                "Beh\u00f6rdenkenntnisse und Beratung zur Einhaltung der DSGVO und Spezialgesetze im Datenschutz (23)",
                "Schulungserfahrung und Schulung der Mitarbeiter im Datenschutz (23)",
                "Pers\u00f6nliche und individuelle Beratung (23)",
                "Beratung zur Rolle des Datenschutzbeauftragten im Unternehmen (23)",
                "Beratung zum Datenschutz-Management-System (23)",
                "Beratung und Sensibilisierung der Mitarbeiter (23)",
                "Beratung hinsichtlich aller durch die DSGVO zu erf\u00fcllenden Verpflichtungen (23)",
                "Rechtliche Pr\u00fcfung und Erstellung der abzuschlie\u00dfenden datenschutzrechtlichen Vereinbarungen (23)",
                "Unterst\u00fctzung bei der F\u00fchrung des Verzeichnisses der Verarbeitungst\u00e4tigkeiten (23)",
                "Schulung von Mitarbeitenden (23)"
            ]
        },
        "Kosten und Transparenz": {
            "title": "Kosten und Transparenz",
            "features": [
                "Planbare Kosten und transparente Preise mit Festpreisen (23)",
                "Kosteng\u00fcnstiger als ein interner Datenschutzbeauftragter (23)",
                "Transparente Kostenstruktur (23)",
                "Transparente und kalkulierbare Kosten durch Pauschalen/Stundenkontingente (23)"
            ]
        },
        "Zertifizierung und Qualifikationen": {
            "title": "Zertifizierung und Qualifikationen",
            "features": [
                "Gepr\u00fcfter & zertifizierter DSGVO-Experte (23)",
                "Zertifizierte Datenschutzexperten (23)",
                "T\u00dcV zertifizierter Datenschutzbeauftragter (23)",
                "Zertifizierter Datenschutzbeauftragte (23)",
                "Fachkundenachweis gem. Art. 37 Abs. 5 DSGVO (23)",
                "Voraussetzungen/Qualifikationen (Anforderungen an die berufliche Qualifikation und Fachwissen) (23)"
            ]
        },
        "Rechtssicherheit und Compliance": {
            "title": "Rechtssicherheit und Compliance",
            "features": [
                "Unterst\u00fctzung auf Grundlage der aktuellen Gesetzeslage und jahrelange Erfahrung im betrieblichen Datenschutz (23)",
                "Rechtssicherheit beim Datenschutz (23)",
                "Erf\u00fcllung der datenschutzrechtlichen Anforderungen der DSGVO und Vermeidung von Bu\u00dfgeldern (23)",
                "Compliance-Unterst\u00fctzung (23)"
            ]
        },
        "Unabh\u00e4ngigkeit und Objektivit\u00e4t": {
            "title": "Unabh\u00e4ngigkeit und Objektivit\u00e4t",
            "features": [
                "Keine Interessenskonflikte: Neutralit\u00e4t gegen\u00fcber der Gesch\u00e4ftsf\u00fchrung, dem Management und den Mitarbeitern (23)",
                "Neutraler Berater vermeidet Interessenkonflikte (23)",
                "Unabh\u00e4ngigkeit und Objektivit\u00e4t (23)",
                "Objektive Sicht auf Unternehmen und Datenverarbeitungsprozesse (23)"
            ]
        },
        "Service und Unterst\u00fctzung": {
            "title": "Service und Unterst\u00fctzung",
            "features": [
                "Unterst\u00fctzung im Arbeitsalltag: Entlastung bei allen Fragen des Datenschutzes, um sich auf das Tagesgesch\u00e4ft zu konzentrieren (23)",
                "Unterst\u00fctzung bei Datenschutzthemen wie Auftragsverarbeitung, Datenschutz-Folgenabsch\u00e4tzungen, Datentransfers, Marketing und Werbung (23)",
                "Unterst\u00fctzung bei der Absicherung des Unternehmens im Datenschutz (23)",
                "Beantwortung von Fragen zum Datenschutz im internationalen Kontext (23)",
                "Hilfe bei der Organisation des Datenschutzes (23)",
                "Hilfe bei der Datenschutz-Folgenabsch\u00e4tzung (DSFA) (23)",
                "Hilfe bei Fehlern, Verst\u00f6\u00dfen und Meldungen an die zust\u00e4ndige Beh\u00f6rde (23)",
                "Formulierung von Antworten auf Beschwerden von Betroffenen (23)",
                "Unterst\u00fctzung beim Dialog mit der Aufsichtsbeh\u00f6rde (23)",
                "Beratung und Vertretung gegen\u00fcber Beh\u00f6rden und Gerichten bei beh\u00f6rdlichen Anfragen und \u00dcberpr\u00fcfungen (23)"
            ]
        },
        "Technische Unterst\u00fctzung und Tools": {
            "title": "Technische Unterst\u00fctzung und Tools",
            "features": [
                "Verf\u00fcgbarkeit von KI-basierten Tools zur Prozessautomatisierung (23)",
                "Bereitstellung von Datenschutzsoftware Proliance 360 (23)",
                "Datenschutz-Management-Portal: Erm\u00f6glicht die Analyse, Bewertung und Dokumentation von Prozessen (23)",
                "Online-Schulungen: Bietet E-Learning-Bereich mit Schulungen f\u00fcr Mitarbeiter (23)",
                "Quick-Check: Erm\u00f6glicht eine Gratis-Vorabbewertung des Datenschutzstandes (23)"
            ]
        },
        "Haftung und Risikominderung": {
            "title": "Haftung und Risikominderung",
            "features": [
                "Stellvertretung Teilhaftung inklusive (23)",
                "180\u00b0 Sicherheit (23)",
                "180\u00b0 IT (23)",
                "180Daten_Zertifiziertes-Fachwissen (23)",
                "180Daten_Pruefungsurkunde (23)",
                "180\u00b0 Sicherheit: Erl\u00e4uterung der Haftung des externen Datenschutzbeauftragten (23)",
                "Vergleich interner und externer Datenschutzbeauftragter: Vor- und Nachteile beider Alternativen (23)",
                "Sanktionen bei untauglicher Benennung: Risiko von Geldbu\u00dfen bei Vernachl\u00e4ssigung der Anforderungen an einen Datenschutzbeauftragten (23)"
            ]
        },
        "Globaler Service und ISO-Zertifizierung": {
            "title": "Globaler Service und ISO-Zertifizierung",
            "features": [
                "Bundesweit t\u00e4tig mit Standorten in Hamburg, Berlin, K\u00f6ln, Frankfurt, Stuttgart und M\u00fcnchen (23)",
                "Deutschland- und weltweiter Service f\u00fcr nationale und internationale Unternehmen, Konzerne und Organisationen (23)",
                "Internationales Team und ISO-Zertifizierung: Das Unternehmen verf\u00fcgt \u00fcber ein internationales Team und ist ISO/IEC 27001:2017 zertifiziert (23)"
            ]
        },
        "Weitere Leistungen": {
            "title": "Weitere Leistungen",
            "features": [
                "180\u00b0 IT: Entwicklung, Implementierung und \u00dcberpr\u00fcfung individueller und effektiver Datenschutzkonzepte (23)",
                "Ganzheitlicher Blick von Recht und Technik (23)",
                "Weltlicher und kirchlicher Datenschutz (23)",
                "Plattform f\u00fcr Datenschutzmanagement (23)",
                "Benennung eines Datenschutzbeauftragten (23)",
                "Inkludierte Beratungsleistungen (23)",
                "Weitere Leistungen (23)"
            ]
        }
    }
}