{
    "summary": "Cookie Policy\n\nWe use technologies, such as cookies, to customise content, to provide social\nmedia features and to analyse traffic to the site. We also share information\nabout your use of our site with our trusted social media, advertising and\nanalytics partners. Cookie policy.\n\nDon't accept.Accept cookies.\n\nMenu\n\n  *   *   *   *   *   * \n\nLogin\n\nLogout\n\nEmail address:\n\nPassword:\n\nForgot password?\n\n## Sinmag Europe | Bakery Machines\n\n  * Home\n  * Machines\n  * Videos\n  * Spare parts\n  * About us\n  * Team\n  * Fairs\n  * Contact\n\n## Like us!\n\n> Sinmag Europe\n\nSINMAG EUROPE NV __NERINGSTRAAT 2 __8370 BLANKENBERGE __ BELGIUM __+32 50 32\n89 05 __Privacy policy __Cookie policy __BE 0875 548 328\n\n",
    "links": "[{\"link\": \"https://sinmageurope.com\", \"text\": \"\"}, {\"link\": \"https://sinmageurope.com/home.php\", \"text\": \"Home\"}, {\"link\": \"https://sinmageurope.com/machines.php\", \"text\": \"Machines\"}, {\"link\": \"https://sinmageurope.com/videos.php\", \"text\": \"Videos\"}, {\"link\": \"https://sinmageurope.com/spareparts.php\", \"text\": \"Spare parts\"}, {\"link\": \"https://sinmageurope.com/about.php\", \"text\": \"About us\"}, {\"link\": \"https://sinmageurope.com/team.php\", \"text\": \"Team\"}, {\"link\": \"https://sinmageurope.com/faires.php\", \"text\": \"Fairs\"}, {\"link\": \"https://sinmageurope.com/contact.php\", \"text\": \"Contact\"}]"
}