{
    "summary": "  * Cloud GPUs\n  * Machine Learning Competitions\n  * Discord\n\n# Cloud GPU Comparison\n\nFind the right cloud GPU provider for your workflow.\n\nToggle column: A100 (80GB) \\- A100 (40GB) \\- H100 \\- 4090 \\- 1080Ti \\- K80 \\-\nV100 \\- A6000 \\- P100 \\- T4 \\- P4 \\- 2080 \\- 3090 \\- A5000 \\- RTX 6000 \\- A40\n| Hide all\n\nName | Credits| A100 (80GB)/h| A100 (40GB)/h| H100/h| Regions| Images|\nNotebooks  \n---|---|---|---|---|---|---|---  \nGoogle Cloud| $350| $5.07| $3.67| -| Worldwide| \u2705| \u2705  \nAmazon AWS| $300| $5.12| $4.096| -| Worldwide| \u2705| \u2705  \nACE Cloud| $300| $3.00| $1.50| -| Worldwide| \u2705| \u274c  \nMicrosoft Azure| $200| $3.67| -| -| Worldwide| \u2705| \u2705  \nVultr| $100| $2.60| -| -| Worldwide| \u2705| \u274c  \nTensorDock| $50| -| -| -| Worldwide| \u2705| \u2705  \nGenesis Cloud| $50| -| -| -| Iceland, Norway| \u2705| \u2705  \nPaperspace| $10| $3.18| $3.09| -| US/Europe| \u2705| \u2705  \nLambda Cloud| $0| $1.50| $1.10| $1.99| US| \u2705| \u2705  \nDataCrunch.io| $0| $2.20| -| -| Finland| \u2705| \u2705  \nJarvis Labs| $0| -| $0.79| -| India| \u2705| \u2705  \nRunPod| $0| $1.89| $0.89| -| Worldwide| \u2705| \u2705  \nCoreWeave| $0| $2.21| $2.06| $4.25| US| \u2705| \u274c  \nLinode| $0| -| -| -| Worldwide| \u2705| \u274c  \nOVHcloud| $0| -| -| -| Worldwide| \u2705| \u274c  \nFluidStack| $0| $1.49| $1.1| -| Worldwide| \u2705| \u274c  \nOblivus Cloud| $0| $2.41| $2.25| -| US| \u2705| \u274c  \nSeeweb| $0| $2.44| -| -| Italy| \u2705| \u274c  \nLatitude.sh| $0| $2.90| -| $4.40| Worldwide| \u2705| \u274c  \nExoscale| $0| -| -| -| Switzerland, Germany| \u2705| \u274c  \nCirrascale| $0| $3.25| $2.87| $4.28| Worldwide| \u2705| \u274c  \nCudo Compute| $0| -| -| -| Worldwide| \u2705| \u274c  \nCrusoe Cloud| $0| $1.65| $1.45| -| US| \u2705| \u274c  \nVast.ai| $0| $1.35| $1.00| -| Worldwide| \u2705| \u2705  \nLeaderGPU| $0| -| -| -| Netherlands| \u274c| \u274c  \n  \nCopyright \u00a9 2023 Cloud ML Ltd | UK company number 14333609 | Submit changes or\nrequests on  GitHub __ | Privacy Policy | Terms |  __ |  __\n\n",
    "links": "[{\"link\": \"https://cloud-gpus.com/\", \"text\": \"Cloud GPUs\"}, {\"link\": \"https://cloud-gpus.com/privacy\", \"text\": \"Privacy Policy\"}, {\"link\": \"https://cloud-gpus.com/terms\", \"text\": \"Terms\"}]",
    "priceAndPlans": "The Wayback Machine - http://web.archive.org/web/20231127123819/https://cloud-\ngpus.com/\n\nCloud GPUs\n\n  * Cloud GPUs\n  * Machine Learning Competitions\n  * Discord\n\n# Cloud GPU Comparison\n\nFind the right cloud GPU provider for your workflow.\n\nToggle column: A100 (40GB) \\- A100 (80GB) \\- H100 \\- 4090 \\- 1080Ti \\- K80 \\-\nV100 \\- A6000 \\- P100 \\- T4 \\- P4 \\- 2080 \\- 3090 \\- A5000 \\- RTX 6000 \\- A40\n| Hide all\n\nName | Credits| A100 (40GB)/h| A100 (80GB)/h| A6000/h| Regions| Images|\nNotebooks  \n---|---|---|---|---|---|---|---  \nGoogle Cloud| $350| $3.67| $5.07| -| Worldwide| \u2705| \u2705  \nAmazon AWS| $300| $4.096| $5.12| -| Worldwide| \u2705| \u2705  \nACE Cloud| $300| $1.50| $3.00| -| Worldwide| \u2705| \u274c  \nMicrosoft Azure| $200| -| $3.67| -| Worldwide| \u2705| \u2705  \nVultr| $100| -| $2.60| -| Worldwide| \u2705| \u274c  \nTensorDock| $50| -| -| $0.40| Worldwide| \u2705| \u2705  \nGenesis Cloud| $50| -| -| -| Iceland, Norway| \u2705| \u2705  \nPaperspace| $10| $3.09| $3.18| $1.89| US/Europe| \u2705| \u2705  \nLambda Cloud| $0| $1.10| $1.50| $0.80| US| \u2705| \u2705  \nDataCrunch.io| $0| -| $2.20| $0.99| Finland| \u2705| \u2705  \nJarvis Labs| $0| $0.79| -| $0.99| India| \u2705| \u2705  \nRunPod| $0| $0.89| $1.89| $0.489| Worldwide| \u2705| \u2705  \nCoreWeave| $0| $2.06| $2.21| $1.28| US| \u2705| \u274c  \nLinode| $0| -| -| -| Worldwide| \u2705| \u274c  \nOVHcloud| $0| -| -| -| Worldwide| \u2705| \u274c  \nFluidStack| $0| $1.1| $1.49| $2.00| Worldwide| \u2705| \u274c  \nOblivus Cloud| $0| $2.25| $2.41| $1.4| US| \u2705| \u274c  \nSeeweb| $0| -| $2.44| $0.75| Italy| \u2705| \u274c  \nLatitude.sh| $0| -| $2.90| -| Worldwide| \u2705| \u274c  \nExoscale| $0| -| -| -| Switzerland, Germany| \u2705| \u274c  \nCirrascale| $0| $2.87| $3.25| $1.12| Worldwide| \u2705| \u274c  \nCudo Compute| $0| -| -| $0.78| Worldwide| \u2705| \u274c  \nCrusoe Cloud| $0| $1.45| $1.65| $0.92| US| \u2705| \u274c  \nVast.ai| $0| $1.00| $1.35| $0.56| Worldwide| \u2705| \u2705  \nLeaderGPU| $0| -| -| $1.86| Netherlands| \u274c| \u274c  \n  \nCopyright \u00a9 2023 Cloud ML Ltd | UK company number 14333609 | Submit changes or\nrequests on  GitHub __ | Privacy Policy | Terms |  __ |  __\n\n"
}