{
    "summary": "Learn\n\nWhat is Starknet?GlossaryFAQ\n\nDevelopers\n\nDevelopers HubDocumentationStarknet BookCairo BookTutorialsRoadmapTools &\nresourcesDevelopers blogStarknet Devs Newsletter\n\nEcosystem\n\ndAppsWalletsStarkGateBridges & on-rampsBlock explorers, indexers & Enhanced\nAPIFull-nodes & RPC servicesSecurity & auditsStarknet Status Page\n\nCommunity\n\n###### START HERE\n\nCommunity Hub\n\n###### GET INVOLVED\n\nEventsEcosystem jobsGovernanceAmbassador programCommunity forumOnline\ncommunities\n\n###### SOCIAL\n\nResources\n\nAll contentMedia kitStarknet EDU newsletterStarknet research hubStarknet Edu\nBlog\n\n`/`\n\n##\n\n# Starknet\n\nStarknet is the secure scaling technology bringing Ethereum\u2019s benefits to the\nworld.\n\nBuild on StarknetLearn the basics\n\n## Unlimited Scale\n\nStarknet utilizes the power of STARK technology to ensure computational\nintegrity. By validating off-chain transactions with advanced math and\ncryptography, Starknet overcomes Ethereum\u2019s scalability limitations. Starknet\nis a Validity Rollup that provides unlimited scale while retaining Ethereum\u2019s\nsecurity and decentralization.\n\nHow Starknet Works \u2192\n\n## Superior UX\n\nStarknet offers efficient and user-friendly experiences by employing Native\nAccount Abstraction. All accounts are smart accounts: their behavior is\ndetermined by their developers rather than at the protocol level. This means\nunparalleled flexibility in account management. Developers can customize their\napplications beyond protocol constraints to elevate user experience and\nsecurity.\n\nDive into Native AA \u2192\n\n## Thriving Ecosystem\n\nStarknet's meteoric rise as a blockchain ecosystem is fueled by its passionate\ncommunity of developers, users, and partners. With the Starknet Stack evolving\nat an astounding pace, this vibrant collective has developed the most\ndecentralized Rollup Stack, enhancing network security, censorship resistance,\nresilience, and transparency.\n\nThe Growing Starknet Stack \u2192\n\n## Creativity Unleashed\n\nStarknet devs are empowered to code solutions that make a difference. Cairo,\nStarknet\u2019s native smart contract language, allows developers to push the\nboundaries of their applications by allowing them to code any kind of business\nlogic. Building with Cairo, developers can let their vision reach its full\npotential on Starknet.\n\nBuild with Cairo \u2192\n\n#### Starknet Devs Newsletter\n\nStay up to date on Starknet news and version updates.\n\n### Start building\n\n### Starknet Docs\n\nRead the official Starknet documentation to build your first contracts and\ndapps.\n\nView docs \u2192\n\n### Developer tutorials\n\nLearn from Starknet's community of developers and builders.\n\nView tutorials  \u2192\n\n### Tools & resources\n\nFind libraries, editor plugins and developer tools to help you start building.\n\nView resources \u2192\n\n### Use Starknet\n\n### Discover dapps\n\nExplore dapps in the Starknet ecosystem \u2013 from Defi to NFTs and gaming.\n\nExplore \u2192\n\n### Find a wallet\n\nLearn about wallets on Starknet and discover the options available.\n\nView wallets \u2192\n\n### Deposit & withdraw funds\n\nLearn how to deposit and withdraw funds for use in the Starknet ecosystem.\n\nView Bridges & on-ramps \u2192\n\n### FAQs\n\n### View all questions\n\nView \u2192\n\n### What is STARK?\n\nView \u2192\n\n### What is Cairo?\n\nView \u2192\n\n### What is Starknet?\n\nView \u2192\n\n#### Learn\n\nWhat is Starknet?GlossaryFAQ\n\n#### Developers\n\nDevelopers HubDocumentationStarknet BookCairo BookTutorialsRoadmapTools &\nresourcesDevelopers blogStarknet Devs Newsletter\n\n#### Ecosystem\n\ndAppsWalletsStarkGateBridges & on-rampsBlock explorers, indexers & Enhanced\nAPIFull-nodes & RPC servicesSecurity & auditsStarknet Status Page\n\n#### Community\n\nCommunity Hub\n\nEventsEcosystem jobsGovernanceAmbassador programCommunity forumOnline\ncommunities\n\n#### Resources\n\nAll contentMedia kitStarknet EDU newsletterStarknet research hub\n\n* * *\n\nPrivacy policyTerms & ConditionsT\ufefferms of Use\n\n* * *\n\n* * *\n\nBuilt with \u2728 by the Starknet community.\n\nPrivacy policyTerms & ConditionsT\ufefferms of Use\n\n",
    "links": "[{\"link\": \"https://www.starknet.io/en/\", \"text\": \"\"}, {\"link\": \"https://www.starknet.io/en/learn/what-is-starknet\", \"text\": \"What is Starknet?\"}, {\"link\": \"https://www.starknet.io/en/learn/glossary\", \"text\": \"Glossary\"}, {\"link\": \"https://www.starknet.io/en/learn/frequently-asked-questions\", \"text\": \"FAQ\"}, {\"link\": \"https://www.starknet.io/en/developers\", \"text\": \"Developers Hub\"}, {\"link\": \"https://www.starknet.io/en/tutorials\", \"text\": \"Tutorials\"}, {\"link\": \"https://www.starknet.io/en/roadmap\", \"text\": \"Roadmap\"}, {\"link\": \"https://www.starknet.io/en/developers/tools-and-resources\", \"text\": \"Tools & resources\"}, {\"link\": \"https://www.starknet.io/en/content/category/developers\", \"text\": \"Developers blog\"}, {\"link\": \"https://www.starknet.io/en/subscribe-newsletter\", \"text\": \"\"}, {\"link\": \"https://www.starknet.io/en/ecosystem/dapps\", \"text\": \"dApps\"}, {\"link\": \"https://www.starknet.io/en/ecosystem/wallets\", \"text\": \"Wallets\"}, {\"link\": \"https://www.starknet.io/en/ecosystem/bridges-and-onramps\", \"text\": \"Bridges & on-ramps\"}, {\"link\": \"https://www.starknet.io/en/ecosystem/block-explorers-indexers-and-enhanced-api\", \"text\": \"Block explorers, indexers & Enhanced API\"}, {\"link\": \"https://www.starknet.io/en/ecosystem/fullnodes-and-rpc-services\", \"text\": \"Full-nodes & RPC services\"}, {\"link\": \"https://www.starknet.io/en/ecosystem/security-and-audits\", \"text\": \"Security & audits\"}, {\"link\": \"https://www.starknet.io/en/community\", \"text\": \"Community Hub\"}, {\"link\": \"https://www.starknet.io/en/events\", \"text\": \"Events\"}, {\"link\": \"https://www.starknet.io/en/jobs\", \"text\": \"Ecosystem jobs\"}, {\"link\": \"https://www.starknet.io/en/community/ambassadors-program\", \"text\": \"Ambassador program\"}, {\"link\": \"https://www.starknet.io/en/community/online-communities\", \"text\": \"Online communities\"}, {\"link\": \"https://www.starknet.io/en/content\", \"text\": \"All content\"}, {\"link\": \"https://www.starknet.io/en/community/media-kit\", \"text\": \"Media kit\"}, {\"link\": \"https://www.starknet.io/en/learn/what-is-starknet\", \"text\": \"\"}, {\"link\": \"https://www.starknet.io/en/content/native-account-abstraction-opening-blockchain-to-new-possibilities\", \"text\": \"\"}, {\"link\": \"https://www.starknet.io/en/content/the-starknet-stacks-growth-spurt\", \"text\": \"\"}, {\"link\": \"https://www.starknet.io/en/tutorials\", \"text\": \"\"}, {\"link\": \"https://www.starknet.io/en/developers/tools-and-resources\", \"text\": \"\"}, {\"link\": \"https://www.starknet.io/en/ecosystem/dapps\", \"text\": \"\"}, {\"link\": \"https://www.starknet.io/en/ecosystem/wallets\", \"text\": \"\"}, {\"link\": \"https://www.starknet.io/en/ecosystem/bridges-and-onramps\", \"text\": \"\"}, {\"link\": \"https://www.starknet.io/en/learn/frequently-asked-questions\", \"text\": \"\"}, {\"link\": \"https://www.starknet.io/en/learn/frequently-asked-questions#toc-cairo\", \"text\": \"\"}, {\"link\": \"https://www.starknet.io/en/learn/frequently-asked-questions#toc-cairo\", \"text\": \"\"}, {\"link\": \"https://www.starknet.io/en/learn/what-is-starknet\", \"text\": \"\"}, {\"link\": \"https://www.starknet.io/en/learn/what-is-starknet\", \"text\": \"What is Starknet?\"}, {\"link\": \"https://www.starknet.io/en/learn/glossary\", \"text\": \"Glossary\"}, {\"link\": \"https://www.starknet.io/en/learn/frequently-asked-questions\", \"text\": \"FAQ\"}, {\"link\": \"https://www.starknet.io/en/developers\", \"text\": \"Developers Hub\"}, {\"link\": \"https://www.starknet.io/en/tutorials\", \"text\": \"Tutorials\"}, {\"link\": \"https://www.starknet.io/en/roadmap\", \"text\": \"Roadmap\"}, {\"link\": \"https://www.starknet.io/en/developers/tools-and-resources\", \"text\": \"Tools & resources\"}, {\"link\": \"https://www.starknet.io/en/content/category/developers\", \"text\": \"Developers blog\"}, {\"link\": \"https://www.starknet.io/en/subscribe-newsletter\", \"text\": \"\"}, {\"link\": \"https://www.starknet.io/en/ecosystem/dapps\", \"text\": \"dApps\"}, {\"link\": \"https://www.starknet.io/en/ecosystem/wallets\", \"text\": \"Wallets\"}, {\"link\": \"https://www.starknet.io/en/ecosystem/bridges-and-onramps\", \"text\": \"Bridges & on-ramps\"}, {\"link\": \"https://www.starknet.io/en/ecosystem/block-explorers-indexers-and-enhanced-api\", \"text\": \"Block explorers, indexers & Enhanced API\"}, {\"link\": \"https://www.starknet.io/en/ecosystem/fullnodes-and-rpc-services\", \"text\": \"Full-nodes & RPC services\"}, {\"link\": \"https://www.starknet.io/en/ecosystem/security-and-audits\", \"text\": \"Security & audits\"}, {\"link\": \"https://www.starknet.io/en/community\", \"text\": \"Community Hub\"}, {\"link\": \"https://www.starknet.io/en/events\", \"text\": \"Events\"}, {\"link\": \"https://www.starknet.io/en/jobs\", \"text\": \"Ecosystem jobs\"}, {\"link\": \"https://www.starknet.io/en/community/ambassadors-program\", \"text\": \"Ambassador program\"}, {\"link\": \"https://www.starknet.io/en/community/online-communities\", \"text\": \"Online communities\"}, {\"link\": \"https://www.starknet.io/en/content\", \"text\": \"All content\"}, {\"link\": \"https://www.starknet.io/en/community/media-kit\", \"text\": \"Media kit\"}, {\"link\": \"https://www.starknet.io/en/legal-disclaimers#toc-privacy-policy\", \"text\": \"Privacy policy\"}, {\"link\": \"https://www.starknet.io/en/legal-disclaimers#toc-terms-and-conditions\", \"text\": \"Terms & Conditions\"}, {\"link\": \"https://www.starknet.io/en/legal-disclaimers#toc-terms-of-use\", \"text\": \"T\ufefferms of Use\"}, {\"link\": \"https://www.starknet.io/en/legal-disclaimers#toc-privacy-policy\", \"text\": \"Privacy policy\"}, {\"link\": \"https://www.starknet.io/en/legal-disclaimers#toc-terms-and-conditions\", \"text\": \"Terms & Conditions\"}, {\"link\": \"https://www.starknet.io/en/legal-disclaimers#toc-terms-of-use\", \"text\": \"T\ufefferms of Use\"}]"
}