{
    "summary": "G\u00e5 vidare till inneh\u00e5ll\n\n  * Home \n  * FRTS | Fr\u00e5n reaktivitet till samspel \n\nFRTS | Fr\u00e5n reaktivitet till samspel\n\n    * FRTS | Fr\u00e5n reaktivitet till samspel \n    * Boka din tr\u00e4ningspass \n\n  * Privattr\u00e4ning \n  * Valptr\u00e4ning \n  * Hundrastning \n\nHundrastning\n\n    * Boka | V\u00e4lj omr\u00e5de \n    * Boka f\u00f6rsta tr\u00e4ff \n    * Ny kund formul\u00e4r \n    * Boka | Vallentuna V\u00e4stra | Ekeby... \n\nBoka | Vallentuna V\u00e4stra | Ekeby...\n\n      * En hund \n      * Tv\u00e5 hundar \n      * Tre hundar \n      * 4 hundar \n\n    * Boka | Vallentuna, S\u00f6dra \n\nBoka | Vallentuna, S\u00f6dra\n\n      * En hund \n      * Tv\u00e5 hundar \n      * Tre hundar \n      * Fyra hundar \n\n    * Boka | T\u00e4by Kyrkby \n\nBoka | T\u00e4by Kyrkby\n\n      * En hund \n      * Tv\u00e5 hundar \n      * Tre hundar \n      * Fyra hundar \n\n    * Boka | Ormsta \n\nBoka | Ormsta\n\n      * En hund \n      * Tv\u00e5 hundar \n      * Tre hundar \n      * Fyra hundar \n\n  * Kattpassning \n\nKattpassning\n\n    * Boka kattpassning \n    * Fyll i blanket: Kattpassning | Instruktioner & viktig information \n\n  * Hundhagen Vallentuna \n  * About ABC \n  * Kontakt \n  * Tips & Artiklar! \n\nTips & Artiklar!\n\n    * Johanna's Rekommenderade Produkter \n    * Lag som g\u00e4ller hundar i Sverige \n\n  * Sociala Medier \n\nSociala Medier\n\n    * Instagram \n    * Youtube \n\nLogga in\n\n  * Instagram\n  * YouTube\n\n#\n\n  * Home\n  * FRTS | Fr\u00e5n reaktivitet till samspel\n    * FRTS | Fr\u00e5n reaktivitet till samspel \n    * Boka din tr\u00e4ningspass \n  * Privattr\u00e4ning\n  * Valptr\u00e4ning\n  * Hundrastning\n    * Boka | V\u00e4lj omr\u00e5de \n    * Boka f\u00f6rsta tr\u00e4ff \n    * Ny kund formul\u00e4r \n    * Boka | Vallentuna V\u00e4stra | Ekeby...\n      * En hund \n      * Tv\u00e5 hundar \n      * Tre hundar \n      * 4 hundar \n    * Boka | Vallentuna, S\u00f6dra\n      * En hund \n      * Tv\u00e5 hundar \n      * Tre hundar \n      * Fyra hundar \n    * Boka | T\u00e4by Kyrkby\n      * En hund \n      * Tv\u00e5 hundar \n      * Tre hundar \n      * Fyra hundar \n    * Boka | Ormsta\n      * En hund \n      * Tv\u00e5 hundar \n      * Tre hundar \n      * Fyra hundar \n  * Kattpassning\n    * Boka kattpassning \n    * Fyll i blanket: Kattpassning | Instruktioner & viktig information \n  * Hundhagen Vallentuna\n  * About ABC\n  * Kontakt\n  * Tips & Artiklar!\n    * Johanna's Rekommenderade Produkter \n    * Lag som g\u00e4ller hundar i Sverige \n  * Sociala Medier\n    * Instagram \n    * Youtube \n\nS\u00f6k\n\nLogga in Varukorg\n\n##  Artikeln har lagts till i varukorgen\n\nSe min varukorg G\u00e5 till kassan  Forts\u00e4tt shoppa\n\nV\u00e4lkommen till ABC Animals\n\nUnder januari \u00e4r ABC \u00f6ppen f\u00f6r bokningar men med begr\u00e4nsade timmar (pga.\nsjukdom)  \nDuring January ABC is open for bookings, however with limited hours (Due to\nillness)\n\nAlla produkter\n\n##  Privattr\u00e4ning, Kurser, Hundrastning, Kattpassning\n\n#\n\nInvalid Password\n\nEnter\n\n## Kontakt\n\nRing/SMS till: (+46) 0728443361 | ABC info@abcanimals.org | Fr\u00e5n Reaktivitet\ntill Samspel info@franreaktivitettillsamspel.com | Karma Hundcenter\njohanna.olsson@karmahundcenter.se\n\n  * Instagram\n  * YouTube\n\n## Spr\u00e5k\n\nSvenska  English\n\nUppdatera spr\u00e5k\n\n## Spr\u00e5k\n\nSvenska\n\n  * Svenska \n  * English \n\nBetalningsmetoder\n\n  * American Express\n  * Apple Pay\n  * Google Pay\n  * Klarna\n  * Maestro\n  * Mastercard\n  * PayPal\n  * Shop Pay\n  * Union Pay\n  * Visa\n\n\u00a9 2024, ABC Animals Powered by Shopify\n\n  * N\u00e4r du g\u00f6r ett urval uppdateras sidan.\n  * \u00d6ppnas i ett nytt f\u00f6nster.\n\n",
    "links": "[{\"link\": \"https://www.abcanimals.org/\", \"text\": \"\\n                            Home\\n                          \"}, {\"link\": \"https://www.abcanimals.org/pages/frts-fran-reaktivitet-till-samspel-1\", \"text\": \"\\n                                          FRTS | Fr\u00e5n reaktivitet till samspel\\n                                        \"}, {\"link\": \"https://www.abcanimals.org/pages/boka-din-traningspass\", \"text\": \"\\n                                          Boka din tr\u00e4ningspass\\n                                        \"}, {\"link\": \"https://www.abcanimals.org/collections/privattraning\", \"text\": \"\\n                            Privattr\u00e4ning\\n                          \"}, {\"link\": \"https://www.abcanimals.org/collections/valptraning\", \"text\": \"\\n                            Valptr\u00e4ning\\n                          \"}, {\"link\": \"https://www.abcanimals.org/pages/hundrastning-valj-omrade\", \"text\": \"\\n                                          Boka | V\u00e4lj omr\u00e5de\\n                                        \"}, {\"link\": \"https://www.abcanimals.org/products/boka-forsta-traff-hundrastning-kattpassning\", \"text\": \"\\n                                          Boka f\u00f6rsta tr\u00e4ff\\n                                        \"}, {\"link\": \"https://www.abcanimals.org/collections/30min-vallentuna-vastra-ekeby-nyby-snapptuna-hundrastning\", \"text\": \"\\n                                                    En hund\\n                                                  \"}, {\"link\": \"https://www.abcanimals.org/collections/2-hundar-vallentuna-vastra-ekeby-nyby-snapptuna-hundrastning\", \"text\": \"\\n                                                    Tv\u00e5 hundar\\n                                                  \"}, {\"link\": \"https://www.abcanimals.org/collections/3-hundar-vallentuna-vastra-ekeby-nyby-snapptuna\", \"text\": \"\\n                                                    Tre hundar\\n                                                  \"}, {\"link\": \"https://www.abcanimals.org/collections/4-hundar-vallentuna-vastra-ekeby-nyby-snapptuna\", \"text\": \"\\n                                                    4 hundar\\n                                                  \"}, {\"link\": \"https://www.abcanimals.org/collections/1-hund-vallentuna-sodra-ballsta-lovisedal-rickeby-hundrastning\", \"text\": \"\\n                                                    En hund\\n                                                  \"}, {\"link\": \"https://www.abcanimals.org/collections/2-hundar-vallentuna-sodra-ballsta-lovisedal-rickeby-hundrastning\", \"text\": \"\\n                                                    Tv\u00e5 hundar\\n                                                  \"}, {\"link\": \"https://www.abcanimals.org/collections/3-hundar-vallentuna-sodra-ballsta-lovisedal-rickeby-hundrastning\", \"text\": \"\\n                                                    Tre hundar\\n                                                  \"}, {\"link\": \"https://www.abcanimals.org/collections/4-hundar-vallentuna-sodra-ballsta-lovisedal-rickeby-hundrastning\", \"text\": \"\\n                                                    Fyra hundar\\n                                                  \"}, {\"link\": \"https://www.abcanimals.org/collections/1-hund-taby-kyrkby-hundrastning\", \"text\": \"\\n                                                    En hund\\n                                                  \"}, {\"link\": \"https://www.abcanimals.org/collections/2-hundar-taby-kyrkby-hundrastning-1\", \"text\": \"\\n                                                    Tv\u00e5 hundar\\n                                                  \"}, {\"link\": \"https://www.abcanimals.org/collections/3-hundar-taby-kyrkby-hundrastning\", \"text\": \"\\n                                                    Tre hundar\\n                                                  \"}, {\"link\": \"https://www.abcanimals.org/collections/4-hundar-taby-kyrkby-hundrastning\", \"text\": \"\\n                                                    Fyra hundar\\n                                                  \"}, {\"link\": \"https://www.abcanimals.org/collections/1-hund-vallentuna-ormsta-hundrastning\", \"text\": \"\\n                                                    En hund\\n                                                  \"}, {\"link\": \"https://www.abcanimals.org/collections/2-hundar-vallentuna-ormsta-hundrastning\", \"text\": \"\\n                                                    Tv\u00e5 hundar\\n                                                  \"}, {\"link\": \"https://www.abcanimals.org/collections/3-hundar-vallentuna-ormsta-hundrastning\", \"text\": \"\\n                                                    Tre hundar\\n                                                  \"}, {\"link\": \"https://www.abcanimals.org/collections/4-hundar-vallentuna-ormsta-hundrastning\", \"text\": \"\\n                                                    Fyra hundar\\n                                                  \"}, {\"link\": \"https://www.abcanimals.org/collections/kattpassning\", \"text\": \"\\n                                          Boka kattpassning\\n                                        \"}, {\"link\": \"https://www.abcanimals.org/collections/hundhagen-vallentuna\", \"text\": \"\\n                            Hundhagen Vallentuna\\n                          \"}, {\"link\": \"https://www.abcanimals.org/pages/about-abc\", \"text\": \"\\n                            About ABC\\n                          \"}, {\"link\": \"https://www.abcanimals.org/pages/contact\", \"text\": \"\\n                            Kontakt\\n                          \"}, {\"link\": \"https://www.abcanimals.org/pages/rekommenderade-produkter\", \"text\": \"\\n                                          Johanna's Rekommenderade Produkter\\n                                        \"}, {\"link\": \"https://www.abcanimals.org/pages/lagstiftning-som-galler-hund-i-sverige\", \"text\": \"\\n                                          Lag som g\u00e4ller hundar i Sverige\\n                                        \"}, {\"link\": \"https://www.abcanimals.org/account/login\", \"text\": \"\"}, {\"link\": \"https://www.abcanimals.org/\", \"text\": \"\"}, {\"link\": \"https://www.abcanimals.org/\", \"text\": \"\"}, {\"link\": \"https://www.abcanimals.org/pages/frts-fran-reaktivitet-till-samspel-1\", \"text\": \"\\n                                FRTS | Fr\u00e5n reaktivitet till samspel\\n                              \"}, {\"link\": \"https://www.abcanimals.org/pages/boka-din-traningspass\", \"text\": \"\\n                                Boka din tr\u00e4ningspass\\n                              \"}, {\"link\": \"https://www.abcanimals.org/collections/privattraning\", \"text\": \"\"}, {\"link\": \"https://www.abcanimals.org/collections/valptraning\", \"text\": \"\"}, {\"link\": \"https://www.abcanimals.org/pages/hundrastning-valj-omrade\", \"text\": \"\\n                                Boka | V\u00e4lj omr\u00e5de\\n                              \"}, {\"link\": \"https://www.abcanimals.org/products/boka-forsta-traff-hundrastning-kattpassning\", \"text\": \"\\n                                Boka f\u00f6rsta tr\u00e4ff\\n                              \"}, {\"link\": \"https://www.abcanimals.org/collections/30min-vallentuna-vastra-ekeby-nyby-snapptuna-hundrastning\", \"text\": \"\\n                                        En hund\\n                                      \"}, {\"link\": \"https://www.abcanimals.org/collections/2-hundar-vallentuna-vastra-ekeby-nyby-snapptuna-hundrastning\", \"text\": \"\\n                                        Tv\u00e5 hundar\\n                                      \"}, {\"link\": \"https://www.abcanimals.org/collections/3-hundar-vallentuna-vastra-ekeby-nyby-snapptuna\", \"text\": \"\\n                                        Tre hundar\\n                                      \"}, {\"link\": \"https://www.abcanimals.org/collections/4-hundar-vallentuna-vastra-ekeby-nyby-snapptuna\", \"text\": \"\\n                                        4 hundar\\n                                      \"}, {\"link\": \"https://www.abcanimals.org/collections/1-hund-vallentuna-sodra-ballsta-lovisedal-rickeby-hundrastning\", \"text\": \"\\n                                        En hund\\n                                      \"}, {\"link\": \"https://www.abcanimals.org/collections/2-hundar-vallentuna-sodra-ballsta-lovisedal-rickeby-hundrastning\", \"text\": \"\\n                                        Tv\u00e5 hundar\\n                                      \"}, {\"link\": \"https://www.abcanimals.org/collections/3-hundar-vallentuna-sodra-ballsta-lovisedal-rickeby-hundrastning\", \"text\": \"\\n                                        Tre hundar\\n                                      \"}, {\"link\": \"https://www.abcanimals.org/collections/4-hundar-vallentuna-sodra-ballsta-lovisedal-rickeby-hundrastning\", \"text\": \"\\n                                        Fyra hundar\\n                                      \"}, {\"link\": \"https://www.abcanimals.org/collections/1-hund-taby-kyrkby-hundrastning\", \"text\": \"\\n                                        En hund\\n                                      \"}, {\"link\": \"https://www.abcanimals.org/collections/2-hundar-taby-kyrkby-hundrastning-1\", \"text\": \"\\n                                        Tv\u00e5 hundar\\n                                      \"}, {\"link\": \"https://www.abcanimals.org/collections/3-hundar-taby-kyrkby-hundrastning\", \"text\": \"\\n                                        Tre hundar\\n                                      \"}, {\"link\": \"https://www.abcanimals.org/collections/4-hundar-taby-kyrkby-hundrastning\", \"text\": \"\\n                                        Fyra hundar\\n                                      \"}, {\"link\": \"https://www.abcanimals.org/collections/1-hund-vallentuna-ormsta-hundrastning\", \"text\": \"\\n                                        En hund\\n                                      \"}, {\"link\": \"https://www.abcanimals.org/collections/2-hundar-vallentuna-ormsta-hundrastning\", \"text\": \"\\n                                        Tv\u00e5 hundar\\n                                      \"}, {\"link\": \"https://www.abcanimals.org/collections/3-hundar-vallentuna-ormsta-hundrastning\", \"text\": \"\\n                                        Tre hundar\\n                                      \"}, {\"link\": \"https://www.abcanimals.org/collections/4-hundar-vallentuna-ormsta-hundrastning\", \"text\": \"\\n                                        Fyra hundar\\n                                      \"}, {\"link\": \"https://www.abcanimals.org/collections/kattpassning\", \"text\": \"\\n                                Boka kattpassning\\n                              \"}, {\"link\": \"https://www.abcanimals.org/collections/hundhagen-vallentuna\", \"text\": \"\"}, {\"link\": \"https://www.abcanimals.org/pages/about-abc\", \"text\": \"\"}, {\"link\": \"https://www.abcanimals.org/pages/contact\", \"text\": \"\"}, {\"link\": \"https://www.abcanimals.org/pages/rekommenderade-produkter\", \"text\": \"\\n                                Johanna's Rekommenderade Produkter\\n                              \"}, {\"link\": \"https://www.abcanimals.org/pages/lagstiftning-som-galler-hund-i-sverige\", \"text\": \"\\n                                Lag som g\u00e4ller hundar i Sverige\\n                              \"}, {\"link\": \"https://www.abcanimals.org/account/login\", \"text\": \"\"}, {\"link\": \"https://www.abcanimals.org/cart\", \"text\": \"\"}, {\"link\": \"https://www.abcanimals.org/cart\", \"text\": \"Se min varukorg\"}, {\"link\": \"https://www.abcanimals.org/collections/all\", \"text\": \"Alla produkter\"}, {\"link\": \"https://www.abcanimals.org/\", \"text\": \"ABC Animals\"}]"
}